econox/__init__.py
econox/_version.py
econox/config.py
econox/optim.py
econox/protocols.py
econox/py.typed
econox/utils.py
econox/logic/__init__.py
econox/logic/distribution.py
econox/logic/dynamics.py
econox/logic/feedback.py
econox/logic/terminal.py
econox/logic/utility.py
econox/methods/__init__.py
econox/methods/analytical.py
econox/methods/base.py
econox/methods/numerical.py
econox/methods/variance.py
econox/solvers/__init__.py
econox/solvers/dynamic_programming.py
econox/solvers/equilibrium.py
econox/structures/__init__.py
econox/structures/model.py
econox/structures/params.py
econox/structures/results.py
econox/workflow/__init__.py
econox/workflow/estimator.py
econox/workflow/simulator.py
econox-0.1.3.dist-info/licenses/LICENSE
econox-0.1.3.dist-info/METADATA
econox-0.1.3.dist-info/WHEEL
econox-0.1.3.dist-info/top_level.txt
econox-0.1.3.dist-info/RECORD
