Metadata-Version: 2.4
Name: econox
Version: 0.1.3
Summary: A JAX-based library for structural modeling and estimation in economics.
Author-email: Haruto Ito <harutoito@g.ecc.u-tokyo.ac.jp>
License: Apache-2.0
Keywords: jax,economics,econometrics,structural-estimation,equinox
Classifier: Programming Language :: Python :: 3
Classifier: License :: OSI Approved :: Apache Software License
Classifier: Operating System :: OS Independent
Requires-Python: >=3.11
License-File: LICENSE
Requires-Dist: equinox>=0.13.2
Requires-Dist: jax>=0.8.1
Requires-Dist: jinja2>=3.1.6
Requires-Dist: lineax>=0.0.8
Requires-Dist: numpy>=2.3.5
Requires-Dist: optimistix>=0.0.11
Requires-Dist: pandas>=2.3.3
Requires-Dist: scipy>=1.16.3
Provides-Extra: dev
Requires-Dist: furo>=2025.9.25; extra == "dev"
Requires-Dist: pytest>=9.0.1; extra == "dev"
Requires-Dist: sphinx>=8.2.3; extra == "dev"
Requires-Dist: sphinx-autodoc-typehints>=3.5.2; extra == "dev"
Dynamic: license-file
